{
  "pkgs": [
    {
      "pkg": "All-Pkgs",
      "count": 71
    },
    {
      "pkg": "arm_pl031",
      "count": 71
    }
  ],
  "checkers": [
    {
      "checker": "All-Checkers",
      "count": 71
    },
    {
      "checker": "Cargo",
      "count": 25
    },
    {
      "checker": "SemverChecks",
      "count": 24
    },
    {
      "checker": "Clippy",
      "count": 8
    },
    {
      "checker": "Outdated",
      "count": 8
    },
    {
      "checker": "Rapx",
      "count": 4
    },
    {
      "checker": "Mirai",
      "count": 2
    },
    {
      "checker": "Fmt",
      "count": 0
    },
    {
      "checker": "Geiger",
      "count": 0
    },
    {
      "checker": "Lockbud",
      "count": 0
    },
    {
      "checker": "Rudra",
      "count": 0
    }
  ],
  "targets": [
    {
      "triple": "All-Targets",
      "count": 71
    },
    {
      "triple": "x86_64-unknown-linux-gnu",
      "count": 20
    },
    {
      "triple": "aarch64-unknown-none",
      "count": 17
    },
    {
      "triple": "riscv64gc-unknown-none-elf",
      "count": 17
    },
    {
      "triple": "x86_64-unknown-none",
      "count": 17
    }
  ],
  "features_sets": [
    {
      "features": "",
      "count": 71
    },
    {
      "features": "All-Features-Sets",
      "count": 71
    }
  ],
  "kinds": {
    "order": [
      "Cargo",
      "Clippy(Error)",
      "Clippy(Warn)",
      "Semver Violation",
      "Audit",
      "Mirai",
      "Rapx",
      "Rudra",
      "Lockbud(Probably)",
      "Lockbud(Possibly)",
      "Outdated",
      "Geiger",
      "Unformatted"
    ],
    "mapping": {
      "cargo": [
        "Cargo"
      ],
      "clippy": [
        "Clippy(Error)",
        "Clippy(Warn)"
      ],
      "semver-checks": [
        "Semver Violation"
      ],
      "audit": [
        "Audit"
      ],
      "mirai": [
        "Mirai"
      ],
      "rapx": [
        "Rapx"
      ],
      "rudra": [
        "Rudra"
      ],
      "lockbud": [
        "Lockbud(Probably)",
        "Lockbud(Possibly)"
      ],
      "outdated": [
        "Outdated"
      ],
      "geiger": [
        "Geiger"
      ],
      "fmt": [
        "Unformatted"
      ]
    }
  }
}