[{"pkg":"lwext4-mkfs","toolchain":"nightly-2024-10-18","checker":"clippy","target":"x86_64-unknown-linux-gnu","cmd":"cargo clippy --target x86_64-unknown-linux-gnu --no-deps --message-format=json","count":1,"ms":17116},{"pkg":"lwext4-mkfs","toolchain":"nightly-2024-10-18","checker":"mirai","target":"x86_64-unknown-linux-gnu","cmd":"cargo +nightly-2023-12-30 mirai --target x86_64-unknown-linux-gnu --message-format=json","count":0,"ms":49},{"pkg":"lwext4-mkfs","toolchain":"nightly-2024-10-18","checker":"lockbud","target":"x86_64-unknown-linux-gnu","cmd":"cargo +nightly-2024-05-21 lockbud -k all -- --target x86_64-unknown-linux-gnu","count":1,"ms":22112},{"pkg":"lwext4-mkfs","toolchain":"nightly-2024-10-18","checker":"rap","target":"x86_64-unknown-linux-gnu","cmd":"cargo +nightly-2024-06-30 rap -F -M","count":1,"ms":33324},{"pkg":"lwext4-mkfs","toolchain":"nightly-2024-10-18","checker":"outdated","target":"x86_64-unknown-linux-gnu","cmd":"cargo outdated -R --exit-code=2","count":0,"ms":68},{"pkg":"lwext4-mkfs","toolchain":"nightly-2024-10-18","checker":"fmt","target":"x86_64-unknown-linux-gnu","cmd":"cargo +nightly-x86_64-unknown-linux-gnu fmt -p lwext4-mkfs -- --emit=json","count":0,"ms":96},{"pkg":"lwext4-rs","toolchain":"nightly-2024-10-18","checker":"clippy","target":"x86_64-unknown-linux-gnu","cmd":"cargo clippy --target x86_64-unknown-linux-gnu --no-deps --message-format=json","count":30,"ms":16911},{"pkg":"lwext4-rs","toolchain":"nightly-2024-10-18","checker":"mirai","target":"x86_64-unknown-linux-gnu","cmd":"cargo +nightly-2023-12-30 mirai --target x86_64-unknown-linux-gnu --message-format=json","count":0,"ms":49},{"pkg":"lwext4-rs","toolchain":"nightly-2024-10-18","checker":"lockbud","target":"x86_64-unknown-linux-gnu","cmd":"cargo +nightly-2024-05-21 lockbud -k all -- --target x86_64-unknown-linux-gnu","count":1,"ms":20553},{"pkg":"lwext4-rs","toolchain":"nightly-2024-10-18","checker":"rap","target":"x86_64-unknown-linux-gnu","cmd":"cargo +nightly-2024-06-30 rap -F -M","count":1,"ms":28307},{"pkg":"lwext4-rs","toolchain":"nightly-2024-10-18","checker":"outdated","target":"x86_64-unknown-linux-gnu","cmd":"cargo outdated -R --exit-code=2","count":0,"ms":64},{"pkg":"lwext4-rs","toolchain":"nightly-2024-10-18","checker":"fmt","target":"x86_64-unknown-linux-gnu","cmd":"cargo +nightly-x86_64-unknown-linux-gnu fmt -p lwext4-rs -- --emit=json","count":0,"ms":117},{"pkg":"lwext4-sys","toolchain":"nightly-2024-10-18","checker":"clippy","target":"x86_64-unknown-linux-gnu","cmd":"cargo clippy --target x86_64-unknown-linux-gnu --no-deps --message-format=json","count":7,"ms":16479},{"pkg":"lwext4-sys","toolchain":"nightly-2024-10-18","checker":"mirai","target":"x86_64-unknown-linux-gnu","cmd":"cargo +nightly-2023-12-30 mirai --target x86_64-unknown-linux-gnu --message-format=json","count":0,"ms":49},{"pkg":"lwext4-sys","toolchain":"nightly-2024-10-18","checker":"lockbud","target":"x86_64-unknown-linux-gnu","cmd":"cargo +nightly-2024-05-21 lockbud -k all -- --target x86_64-unknown-linux-gnu","count":1,"ms":20102},{"pkg":"lwext4-sys","toolchain":"nightly-2024-10-18","checker":"rap","target":"x86_64-unknown-linux-gnu","cmd":"cargo +nightly-2024-06-30 rap -F -M","count":0,"ms":24064},{"pkg":"lwext4-sys","toolchain":"nightly-2024-10-18","checker":"outdated","target":"x86_64-unknown-linux-gnu","cmd":"cargo outdated -R --exit-code=2","count":0,"ms":63},{"pkg":"lwext4-sys","toolchain":"nightly-2024-10-18","checker":"fmt","target":"x86_64-unknown-linux-gnu","cmd":"cargo +nightly-x86_64-unknown-linux-gnu fmt -p lwext4-sys -- --emit=json","count":1,"ms":109}]