[{"pkg":"lwext4_rust","toolchain":"nightly-2024-10-23","checker":"clippy","target":"riscv64gc-unknown-none-elf","cmd":"cargo clippy --target riscv64gc-unknown-none-elf --no-deps --message-format=json","count":5,"ms":536},{"pkg":"lwext4_rust","toolchain":"nightly-2024-10-23","checker":"clippy","target":"x86_64-unknown-linux-gnu","cmd":"cargo clippy --target x86_64-unknown-linux-gnu --no-deps --message-format=json","count":5,"ms":711},{"pkg":"lwext4_rust","toolchain":"nightly-2024-10-23","checker":"mirai","target":"x86_64-unknown-linux-gnu","cmd":"cargo +nightly-2023-12-30 mirai --target x86_64-unknown-linux-gnu --message-format=json","count":0,"ms":806},{"pkg":"lwext4_rust","toolchain":"nightly-2024-10-23","checker":"lockbud","target":"riscv64gc-unknown-none-elf","cmd":"cargo +nightly-2024-05-21 lockbud -k all -- --target riscv64gc-unknown-none-elf","count":1,"ms":626},{"pkg":"lwext4_rust","toolchain":"nightly-2024-10-23","checker":"lockbud","target":"x86_64-unknown-linux-gnu","cmd":"cargo +nightly-2024-05-21 lockbud -k all -- --target x86_64-unknown-linux-gnu","count":1,"ms":808},{"pkg":"lwext4_rust","toolchain":"nightly-2024-10-23","checker":"rap","target":"x86_64-unknown-linux-gnu","cmd":"cargo +nightly-2024-06-30 rap -F -M","count":0,"ms":1169},{"pkg":"lwext4_rust","toolchain":"nightly-2024-10-23","checker":"outdated","target":"riscv64gc-unknown-none-elf","cmd":"cargo outdated -R --exit-code=2","count":1,"ms":227},{"pkg":"lwext4_rust","toolchain":"nightly-2024-10-23","checker":"outdated","target":"x86_64-unknown-linux-gnu","cmd":"cargo outdated -R --exit-code=2","count":1,"ms":231},{"pkg":"lwext4_rust","toolchain":"nightly-2024-10-23","checker":"fmt","target":"riscv64gc-unknown-none-elf","cmd":"cargo +nightly-2024-10-24-x86_64-unknown-linux-gnu fmt -p lwext4_rust -- --emit=json","count":18,"ms":120},{"pkg":"lwext4_rust","toolchain":"nightly-2024-10-23","checker":"fmt","target":"x86_64-unknown-linux-gnu","cmd":"cargo +nightly-2024-10-24-x86_64-unknown-linux-gnu fmt -p lwext4_rust -- --emit=json","count":18,"ms":123},{"pkg":"lwext4_rust_examples","toolchain":"nightly-2024-01-31","checker":"clippy","target":"riscv64gc-unknown-none-elf","cmd":"cargo clippy --target riscv64gc-unknown-none-elf --no-deps --message-format=json","count":0,"ms":120},{"pkg":"lwext4_rust_examples","toolchain":"nightly-2024-01-31","checker":"lockbud","target":"riscv64gc-unknown-none-elf","cmd":"cargo +nightly-2024-05-21 lockbud -k all -- --target riscv64gc-unknown-none-elf","count":1,"ms":3265},{"pkg":"lwext4_rust_examples","toolchain":"nightly-2024-01-31","checker":"outdated","target":"riscv64gc-unknown-none-elf","cmd":"cargo outdated -R --exit-code=2","count":0,"ms":97},{"pkg":"lwext4_rust_examples","toolchain":"nightly-2024-01-31","checker":"fmt","target":"riscv64gc-unknown-none-elf","cmd":"cargo +nightly-2024-10-24-x86_64-unknown-linux-gnu fmt -p lwext4_rust_examples -- --emit=json","count":17,"ms":103}]